veloxx-0.3.2.dist-info/METADATA
veloxx-0.3.2.dist-info/WHEEL
veloxx-0.3.2.dist-info/licenses/LICENSE
veloxx/__init__.py
veloxx/veloxx.cp313-win_amd64.pyd
veloxx-0.3.2.dist-info/RECORD
