Metadata-Version: 2.4
Name: veloxx
Version: 0.3.2
Classifier: Development Status :: 4 - Beta
Classifier: Intended Audience :: Developers
Classifier: License :: OSI Approved :: MIT License
Classifier: Programming Language :: Python :: 3
Classifier: Programming Language :: Python :: 3.7
Classifier: Programming Language :: Python :: 3.8
Classifier: Programming Language :: Python :: 3.9
Classifier: Programming Language :: Python :: 3.10
Classifier: Programming Language :: Python :: 3.11
Classifier: Programming Language :: Python :: 3.12
Classifier: Programming Language :: Rust
Classifier: Topic :: Scientific/Engineering
Classifier: Topic :: Scientific/Engineering :: Information Analysis
Classifier: Topic :: Scientific/Engineering :: Artificial Intelligence
Classifier: Topic :: Scientific/Engineering :: Visualization
Classifier: Topic :: Database
Classifier: Topic :: Software Development :: Libraries :: Python Modules
License-File: LICENSE
Summary: Veloxx: High-performance, lightweight Python library for in-memory data processing and analytics. Built on Rust for blazing speed and memory efficiency. Features DataFrames, Series, advanced I/O (CSV, JSON, Parquet), machine learning (linear regression, K-means, logistic regression), time-series analysis, data visualization, and parallel processing. Perfect for data science, analytics, and performance-critical applications where speed and memory usage matter.
Keywords: dataframe,analytics,data-processing,machine-learning,time-series,statistics,csv,json,parquet,visualization,rust,performance,parallel,data-science,pandas-alternative
Author-email: Conqxeror <conqxeror@gmail.com>
License: MIT
Requires-Python: >=3.7
Project-URL: Homepage, https://github.com/Conqxeror/veloxx
Project-URL: Repository, https://github.com/Conqxeror/veloxx
